
{"items":[{"name":"Getting started","href":"../index.html","topicHref":"../index.html"},{"name":"State Persistence","href":"statepersistence.html","topicHref":"statepersistence.html"},{"name":"Parallelism","href":"parallelism.html","topicHref":"parallelism.html"},{"name":"Connectors","items":[{"name":"Catalogs","href":"connectors/catalogs.html","topicHref":"connectors/catalogs.html"},{"name":"Configuration Data","href":"connectors/configurationdata.html","topicHref":"connectors/configurationdata.html"},{"name":"SQL Server Connector","href":"connectors/sqlserver.html","topicHref":"connectors/sqlserver.html"},{"name":"Delta Lake Connector","href":"connectors/deltalake.html","topicHref":"connectors/deltalake.html"},{"name":"MongoDB Connector","href":"connectors/mongodb.html","topicHref":"connectors/mongodb.html"},{"name":"CosmosDB Connector","href":"connectors/cosmosdb.html","topicHref":"connectors/cosmosdb.html"},{"name":"Elasticsearch Connector","href":"connectors/elasticsearch.html","topicHref":"connectors/elasticsearch.html"},{"name":"Kafka Connector","href":"connectors/kafka.html","topicHref":"connectors/kafka.html"},{"name":"Custom Data Source","href":"connectors/customdata.html","topicHref":"connectors/customdata.html"},{"name":"Sharepoint Connector","href":"connectors/sharepoint.html","topicHref":"connectors/sharepoint.html"},{"name":"OpenFGA Connector","href":"connectors/openfga.html","topicHref":"connectors/openfga.html"},{"name":"AuthZed/SpiceDB Connector","href":"connectors/spicedb.html","topicHref":"connectors/spicedb.html"},{"name":"Permify Connector","href":"connectors/permify.html","topicHref":"connectors/permify.html"},{"name":"Files Connector","href":"connectors/files.html","topicHref":"connectors/files.html"},{"name":"Qdrant connector","href":"connectors/qdrant.html","topicHref":"connectors/qdrant.html"},{"name":"Starrocks Connector","href":"connectors/starrocks.html","topicHref":"connectors/starrocks.html"}]},{"name":"Deployment","items":[{"name":"Pause And Resume","href":"deployment/pauseresume.html","topicHref":"deployment/pauseresume.html"}]},{"name":"Monitoring","items":[{"name":"General Metrics","href":"monitoring/generalmetrics.html","topicHref":"monitoring/generalmetrics.html"},{"name":"Health checks","href":"monitoring/healthchecks.html","topicHref":"monitoring/healthchecks.html"},{"name":"Prometheus","href":"monitoring/prometheus.html","topicHref":"monitoring/prometheus.html"},{"name":"Azure Monitor","href":"monitoring/azuremonitor.html","topicHref":"monitoring/azuremonitor.html"},{"name":"OpenLineage","href":"monitoring/openlineage.html","topicHref":"monitoring/openlineage.html"}]},{"name":"Operators","items":[{"name":"Projection Operator","href":"operators/projection.html","topicHref":"operators/projection.html"},{"name":"Filter Operator","href":"operators/filter.html","topicHref":"operators/filter.html"},{"name":"Join Operators","href":"operators/join.html","topicHref":"operators/join.html"},{"name":"Normalization Operator","href":"operators/normalization.html","topicHref":"operators/normalization.html"},{"name":"Set Operator","href":"operators/set.html","topicHref":"operators/set.html"},{"name":"Aggregate Operator","href":"operators/aggregate.html","topicHref":"operators/aggregate.html"},{"name":"Iteration Operator","href":"operators/iteration.html","topicHref":"operators/iteration.html"},{"name":"Buffer Operator","href":"operators/buffer.html","topicHref":"operators/buffer.html"},{"name":"Top N Operator","href":"operators/topn.html","topicHref":"operators/topn.html"},{"name":"Table Function Operator","href":"operators/tablefunction.html","topicHref":"operators/tablefunction.html"},{"name":"Window Operator","href":"operators/window.html","topicHref":"operators/window.html"}]},{"name":"Expressions","items":[{"name":"Scalar Functions","items":[{"name":"Arithmetic Functions","href":"expressions/scalarfunctions/arithmetic.html","topicHref":"expressions/scalarfunctions/arithmetic.html"},{"name":"Boolean Functions","href":"expressions/scalarfunctions/boolean.html","topicHref":"expressions/scalarfunctions/boolean.html"},{"name":"Comparison Functions","href":"expressions/scalarfunctions/comparison.html","topicHref":"expressions/scalarfunctions/comparison.html"},{"name":"String Functions","href":"expressions/scalarfunctions/string.html","topicHref":"expressions/scalarfunctions/string.html"},{"name":"Rounding Functions","href":"expressions/scalarfunctions/rounding.html","topicHref":"expressions/scalarfunctions/rounding.html"},{"name":"Datetime Functions","href":"expressions/scalarfunctions/datetime.html","topicHref":"expressions/scalarfunctions/datetime.html"},{"name":"Check Functions","href":"expressions/scalarfunctions/check.html","topicHref":"expressions/scalarfunctions/check.html"},{"name":"List Functions","href":"expressions/scalarfunctions/list.html","topicHref":"expressions/scalarfunctions/list.html"},{"name":"Hash Functions","href":"expressions/scalarfunctions/hash.html","topicHref":"expressions/scalarfunctions/hash.html"},{"name":"Logarithmic Functions","href":"expressions/scalarfunctions/logarithmic.html","topicHref":"expressions/scalarfunctions/logarithmic.html"}]},{"name":"Aggregate Functions","items":[{"name":"Generic Functions","href":"expressions/aggregatefunctions/generic.html","topicHref":"expressions/aggregatefunctions/generic.html"},{"name":"Arithmetic Functions","href":"expressions/aggregatefunctions/arithmetic.html","topicHref":"expressions/aggregatefunctions/arithmetic.html"},{"name":"List Functions","href":"expressions/aggregatefunctions/list.html","topicHref":"expressions/aggregatefunctions/list.html"},{"name":"String functions","href":"expressions/aggregatefunctions/string.html","topicHref":"expressions/aggregatefunctions/string.html"}]},{"name":"Table Functions","href":"expressions/tablefunctions/index.html","topicHref":"expressions/tablefunctions/index.html","items":[{"name":"Generic Functions","href":"expressions/tablefunctions/generic.html","topicHref":"expressions/tablefunctions/generic.html"}]},{"name":"Window Functions","href":"expressions/windowfunctions/index.html","topicHref":"expressions/windowfunctions/index.html","items":[{"name":"Arithmetic Functions","href":"expressions/windowfunctions/arithmetic.html","topicHref":"expressions/windowfunctions/arithmetic.html"},{"name":"Generic Functions","href":"expressions/windowfunctions/generic.html","topicHref":"expressions/windowfunctions/generic.html"}]},{"name":"Specialized Expressions","href":"expressions/specializedexpressions.html","topicHref":"expressions/specializedexpressions.html"}]},{"name":"SQL","href":"sql/index.html","topicHref":"sql/index.html","items":[{"name":"Table Provider","href":"sql/tableprovider.html","topicHref":"sql/tableprovider.html"},{"name":"Create Table","href":"sql/createtable.html","topicHref":"sql/createtable.html"},{"name":"Create View","href":"sql/createview.html","topicHref":"sql/createview.html"},{"name":"Select","href":"sql/select/index.html","topicHref":"sql/select/index.html","items":[{"name":"Union","href":"sql/select/union.html","topicHref":"sql/select/union.html"},{"name":"Top N","href":"sql/select/topn.html","topicHref":"sql/select/topn.html"},{"name":"Except","href":"sql/select/except.html","topicHref":"sql/select/except.html"},{"name":"Intersect","href":"sql/select/intersect.html","topicHref":"sql/select/intersect.html"}]},{"name":"Insert Into","href":"sql/insertinto.html","topicHref":"sql/insertinto.html"},{"name":"Recursion","href":"sql/recursion.html","topicHref":"sql/recursion.html"}]},{"name":"Testing","href":"testing/index.html","topicHref":"testing/index.html","items":[{"name":"Integration Testing","href":"testing/integrationtests.html","topicHref":"testing/integrationtests.html"},{"name":".NET Aspire Testing","href":"testing/aspiretesting.html","topicHref":"testing/aspiretesting.html"}]},{"name":"Internal","items":[{"name":"Project Structure","href":"internal/projectstructure.html","topicHref":"internal/projectstructure.html"},{"name":"Reservoir Storage System","href":"internal/reservoir/index.html","topicHref":"internal/reservoir/index.html"},{"name":"Storage","items":[{"name":"Persistent Storage Rules","href":"internal/storage/persistentrules.html","topicHref":"internal/storage/persistentrules.html"},{"name":"B+ Tree","href":"internal/storage/bplustree.html","topicHref":"internal/storage/bplustree.html"},{"name":"Object State","href":"internal/storage/objectstate.html","topicHref":"internal/storage/objectstate.html"}]}]}],"pdf":false}
